neov/__init__.py
neov/neov.py
neov-0.2.0.dist-info/METADATA
neov-0.2.0.dist-info/WHEEL
neov-0.2.0.dist-info/top_level.txt
neov-0.2.0.dist-info/RECORD
