Metadata-Version: 2.4
Name: neov
Version: 0.2.0
Summary: telegram
Home-page: https://github.com/ваш_username/qtpv
Author: matvey
Author-email: cbisk@gmail.com
Classifier: Programming Language :: Python :: 3
Classifier: License :: OSI Approved :: MIT License
Classifier: Operating System :: OS Independent
Requires-Python: >=3.6
Requires-Dist: requests
Dynamic: author
Dynamic: author-email
Dynamic: classifier
Dynamic: description-content-type
Dynamic: home-page
Dynamic: requires-dist
Dynamic: requires-python
Dynamic: summary
